Products.CMFDefault-2.3.0-py2.7-nspkg.pth
Products/CMFDefault/DefaultWorkflow.py
Products/CMFDefault/DiscussionItem.py
Products/CMFDefault/DiscussionTool.py
Products/CMFDefault/Document.py
Products/CMFDefault/DublinCore.py
Products/CMFDefault/Favorite.py
Products/CMFDefault/File.py
Products/CMFDefault/Image.py
Products/CMFDefault/Link.py
Products/CMFDefault/MembershipTool.py
Products/CMFDefault/MetadataTool.py
Products/CMFDefault/NewsItem.py
Products/CMFDefault/Portal.py
Products/CMFDefault/PropertiesTool.py
Products/CMFDefault/RegistrationTool.py
Products/CMFDefault/SkinnedFolder.py
Products/CMFDefault/SyndicationInfo.py
Products/CMFDefault/SyndicationTool.py
Products/CMFDefault/URLTool.py
Products/CMFDefault/__init__.py
Products/CMFDefault/configure.zcml
Products/CMFDefault/content.zcml
Products/CMFDefault/directories.zcml
Products/CMFDefault/exceptions.py
Products/CMFDefault/exportimport.zcml
Products/CMFDefault/factory.py
Products/CMFDefault/permissions.py
Products/CMFDefault/profiles.zcml
Products/CMFDefault/setuphandlers.py
Products/CMFDefault/testing.py
Products/CMFDefault/tool.gif
Products/CMFDefault/utils.py
Products/CMFDefault/browser/README.txt
Products/CMFDefault/browser/__init__.py
Products/CMFDefault/browser/configure.zcml
Products/CMFDefault/browser/test_utils.py
Products/CMFDefault/browser/utils.py
Products/CMFDefault/browser/admin/TODO.rst
Products/CMFDefault/browser/admin/__init__.py
Products/CMFDefault/browser/admin/config.pt
Products/CMFDefault/browser/admin/config.py
Products/CMFDefault/browser/admin/configure.zcml
Products/CMFDefault/browser/admin/interfaces.py
Products/CMFDefault/browser/admin/syndication.pt
Products/CMFDefault/browser/admin/syndication.py
Products/CMFDefault/browser/admin/tests/__init__.py
Products/CMFDefault/browser/admin/tests/portal_config.txt
Products/CMFDefault/browser/admin/tests/test_config.py
Products/CMFDefault/browser/admin/tests/test_syndication.py
Products/CMFDefault/browser/content/TODO.rst
Products.CMFDefault-2.3.0.dist-info/LICENSE.txt
Products.CMFDefault-2.3.0.dist-info/METADATA
Products.CMFDefault-2.3.0.dist-info/WHEEL
Products.CMFDefault-2.3.0.dist-info/entry_points.txt
Products.CMFDefault-2.3.0.dist-info/namespace_packages.txt
Products.CMFDefault-2.3.0.dist-info/test_info.txt
Products.CMFDefault-2.3.0.dist-info/top_level.txt
Products.CMFDefault-2.3.0.dist-info/RECORD
