Metadata-Version: 2.1
Name: Products.CMFDefault
Version: 2.3.0
Summary: Default product for the Zope Content Management Framework
Home-page: https://github.com/zopefoundation/Products.CMFDefault
Author: Zope Foundation and Contributors
Author-email: zope-cmf@zope.org
License: ZPL 2.1
Project-URL: Issue Tracker, https://github.com/zopefoundation/Products.CMFDefault/issues
Project-URL: Sources, https://github.com/zopefoundation/Products.CMFDefault
Keywords: web application server zope zope2 cmf
Platform: UNKNOWN
Classifier: Development Status :: 5 - Production/Stable
Classifier: Framework :: Plone
Classifier: Framework :: Zope :: 2
Classifier: Framework :: Zope2
Classifier: Intended Audience :: Developers
Classifier: License :: OSI Approved :: Zope Public License
Classifier: Programming Language :: Python :: 2
Classifier: Programming Language :: Python :: 2.7
Classifier: Programming Language :: Python :: Implementation :: CPython
Classifier: Topic :: Software Development :: Libraries :: Application Frameworks
Requires-Python: >=2.7, <3.0
Requires-Dist: setuptools
Requires-Dist: Zope2 (>=2.13.12)
Requires-Dist: Products.CMFCore (<2.4)
Requires-Dist: Products.GenericSetup (<1.9)
Requires-Dist: Products.MailHost
Requires-Dist: Products.PythonScripts
Requires-Dist: five.globalrequest (<99)
Requires-Dist: five.localsitemanager (<3)
Requires-Dist: zope.formlib
Provides-Extra: docs
Requires-Dist: Sphinx ; extra == 'docs'
Requires-Dist: repoze.sphinx.autointerface ; extra == 'docs'
Requires-Dist: pkginfo ; extra == 'docs'
Provides-Extra: locales
Requires-Dist: zope.app.locales ; extra == 'locales'
Provides-Extra: test
Requires-Dist: Products.DCWorkflow (<2.4) ; extra == 'test'
